README.rst
setup.py
bitbucket_sync/__init__.py
bitbucket_sync/main.py
bitbucket_sync.egg-info/PKG-INFO
bitbucket_sync.egg-info/SOURCES.txt
bitbucket_sync.egg-info/dependency_links.txt
bitbucket_sync.egg-info/entry_points.txt
bitbucket_sync.egg-info/requires.txt
bitbucket_sync.egg-info/top_level.txt