Metadata-Version: 1.0
Name: bitbucket-sync
Version: 0.3.2
Summary: bitbucket-sync synchronize locally all the repositories of a bitbucket account
Home-page: https://github.com/gautier/bitbucket-sync
Author: Gautier Hayoun
Author-email: ghayoun@gmail.com
License: MIT
Platform: UNKNOWN
